mhealth_video_process/__init__.py
mhealth_video_process/exiftool.exe
mhealth_video_process/process.py
mhealth_video_process-0.8.dist-info/LICENSE
mhealth_video_process-0.8.dist-info/METADATA
mhealth_video_process-0.8.dist-info/WHEEL
mhealth_video_process-0.8.dist-info/top_level.txt
mhealth_video_process-0.8.dist-info/RECORD
