Metadata-Version: 2.1
Name: mhealth-video-process
Version: 0.8
Summary: A pacakge to process video files.
Home-page: https://bitbucket.org/mhealthresearchgroup/video-process.git
Author: binodtc
Author-email: binod.thapachhetry@gmail.com
License: UNKNOWN
Platform: UNKNOWN
Classifier: Programming Language :: Python :: 3
Classifier: License :: OSI Approved :: MIT License
Classifier: Operating System :: OS Independent
Requires-Python: >=3.6
License-File: LICENSE
Requires-Dist: get-video-properties (==0.1.1)
